django_guardian-3.1.3.dist-info/licenses/LICENSE
guardian/__init__.py
guardian/admin.py
guardian/apps.py
guardian/backends.py
guardian/checks.py
guardian/compat.py
guardian/core.py
guardian/ctypes.py
guardian/decorators.py
guardian/exceptions.py
guardian/forms.py
guardian/managers.py
guardian/mixins.py
guardian/py.typed
guardian/shortcuts.py
guardian/utils.py
guardian/conf/__init__.py
guardian/conf/settings.py
guardian/locale/es/LC_MESSAGES/django.mo
guardian/locale/es/LC_MESSAGES/django.po
guardian/locale/fr/LC_MESSAGES/django.mo
guardian/locale/fr/LC_MESSAGES/django.po
guardian/locale/nl/LC_MESSAGES/django.mo
guardian/locale/nl/LC_MESSAGES/django.po
guardian/locale/pl/LC_MESSAGES/django.mo
guardian/locale/pl/LC_MESSAGES/django.po
guardian/locale/pt_BR/LC_MESSAGES/django.mo
guardian/locale/pt_BR/LC_MESSAGES/django.po
guardian/locale/ru/LC_MESSAGES/django.mo
guardian/locale/ru/LC_MESSAGES/django.po
guardian/locale/zh_Hans/LC_MESSAGES/django.mo
guardian/locale/zh_Hans/LC_MESSAGES/django.po
guardian/management/__init__.py
guardian/management/commands/__init__.py
guardian/management/commands/clean_orphan_obj_perms.py
guardian/migrations/0001_initial.py
guardian/migrations/0002_generic_permissions_index.py
guardian/migrations/0003_remove_groupobjectpermission_guardian_gr_content_ae6aec_idx_and_more.py
guardian/migrations/__init__.py
guardian/models/__init__.py
guardian/models/models.py
guardian/static/guardian/img/icon-no.svg
guardian/static/guardian/img/icon-yes.svg
guardian/templates/admin/guardian/contrib/grappelli/field.html
guardian/templates/admin/guardian/contrib/grappelli/obj_perms_manage.html
guardian/templates/admin/guardian/contrib/grappelli/obj_perms_manage_group.html
guardian/templates/admin/guardian/contrib/grappelli/obj_perms_manage_user.html
guardian/templates/admin/guardian/model/change_form.html
guardian/templates/admin/guardian/model/field.html
guardian/templates/admin/guardian/model/obj_perms_manage.html
guardian/templates/admin/guardian/model/obj_perms_manage_group.html
django_guardian-3.1.3.dist-info/METADATA
django_guardian-3.1.3.dist-info/WHEEL
django_guardian-3.1.3.dist-info/top_level.txt
django_guardian-3.1.3.dist-info/RECORD
