Metadata-Version: 2.4
Name: django-guardian
Version: 3.1.3
Summary: Per object permissions for Django
Author: Chris Maggiuli, Bona Fide IT GmbH, Columbia University, SIS Development and Application Services
Author-email: Lukasz Balcerzak <lukaszbalcerzak@gmail.com>, Cesar Canassa <cesar.canassa@gmail.com>, Vincent Driessen <vincent@datafox.nl>, John Hensley <john@fairviewcomputing.com>, Ramanan Sivaranjan <ramanan@funkaoshi.com>, Woosuk Suh <pipoket88@gmail.com>, Bojan Mihelac <bmihelac@mihelac.org>, Rafael Ponieman <rafadev@gmail.com>, Daniel Sokolowski <daniel.sokolowski@danols.com>, Ali Lozano <alilozanoc@gmail.com>, BJ Dierkes <derks@bjdierkes.com>, Rach Belaid <rachid.belaid@gmail.com>, Michae
Maintainer: Michael K., Chris Maggiuli, Bona Fide IT GmbH
Maintainer-email: Tom Clark <django-guardian@octue.com>, Brian May <brian@microcomaustralia.com.au>, Lukasz Balcerzak <lukaszbalcerzak@gmail.com>, Adam Dobrawy <guardian@jawnosc.tk>, David Graham <dpgraham4401@gmail.com>, Sezer BOZKIR <admin@sezerbozkir.com>
License: BSD-2-Clause
Project-URL: Homepage, https://github.com/django-guardian/django-guardian
Project-URL: Documentation, https://django-guardian.readthedocs.io/
Project-URL: Repository, https://github.com/django-guardian/django-guardian
Project-URL: Issues, https://github.com/me/spam/issues
Project-URL: Changelog, https://github.com/django-guardian/django-guardian/releases
Keywords: django,permissions,authorization,object,row,level
Classifier: Development Status :: 5 - Production/Stable
Classifier: Intended Audience :: Developers
Classifier: Environment :: Web Environment
Classifier: Topic :: Software Development :: Libraries :: Python Modules
Classifier: License :: OSI Approved :: BSD License
Classifier: Framework :: Django
Classifier: Framework :: Django :: 3.2
Classifier: Framework :: Django :: 4.1
Classifier: Framework :: Django :: 4.2
Classifier: Framework :: Django :: 5.0
Classifier: Framework :: Django :: 5.1
Classifier: Framework :: Django :: 5.2
Classifier: Programming Language :: Python
Classifier: Programming Language :: Python :: 3 :: Only
Classifier: Programming Language :: Python :: 3.9
Classifier: Programming Language :: Python :: 3.10
Classifier: Programming Language :: Python :: 3.11
Classifier: Programming Language :: Python :: 3.12
Classifier: Programming Language :: Python :: 3.13
Classifier: Operating System :: OS Independent
Classifier: Topic :: Security
Requires-Python: >=3.9
License-File: LICENSE
Requires-Dist: django>=3.2
Requires-Dist: typing_extensions>=4.12.0; python_version < "3.13"
Dynamic: license-file
